pyroll/hitchcock_roll_flattening.py
pyroll_hitchcock_roll_flattening-3.0.0.dist-info/METADATA
pyroll_hitchcock_roll_flattening-3.0.0.dist-info/WHEEL
pyroll_hitchcock_roll_flattening-3.0.0.dist-info/licenses/LICENSE
pyroll_hitchcock_roll_flattening-3.0.0.dist-info/RECORD
