Metadata-Version: 2.3
Name: pyroll-hitchcock-roll-flattening
Version: 3.0.0
Summary: PyRolL plugin providing the roll flattening model from J. Hitchcock.
Author-email: Christoph Renzing <christoph.renzing@imf.tu-freiberg.de>, Max Weiner <max.weiner@imf.tu-freiberg.de>
License-Expression: BSD-3-Clause
License-File: LICENSE
Classifier: Intended Audience :: Manufacturing
Classifier: Intended Audience :: Science/Research
Classifier: Operating System :: OS Independent
Classifier: Topic :: Scientific/Engineering
Requires-Python: >=3.9
Requires-Dist: pyroll-core~=3.0
